{
  "metadata": {
    "description": "",
    "user": "luke",
    "ctime": "1689044967",
    "version": "1.0.0",
    "references": [
      {
        "filename": "X:/Art/1_Assets/2_Rig/MAYA/SkinnedMeshes/Weapon/SK_Player_Weapon_Katana_001_rig.mb",
        "unresolved": "X:/Art/1_Assets/2_Rig/MAYA/SkinnedMeshes/Weapon/SK_Player_Weapon_Katana_001_rig.mb",
        "namespace": ":SK_Player_Weapon_Katana_001_rig",
        "node": "SK_Player_Weapon_Katana_001_rigRN"
      }
    ],
    "mayaVersion": "2023",
    "mayaSceneFile": "X:/Art/1_Assets/3_Animation/MAYA/Player/Katana/ANI_Player_Katana_Idle_001_v01.mb"
  }
,
  "objects": {
    "SK_Player_Weapon_Katana_001_rig:Main": {
      "attrs": {
        "scaleZ": {
          "type": "double",
          "value": 1.0
        },
        "scaleX": {
          "type": "double",
          "value": 1.0
        },
        "translateY": {
          "type": "doubleLinear",
          "value": 75.58578082375905
        },
        "rotateZ": {
          "type": "doubleAngle",
          "value": -4.451381382195025
        },
        "rotateX": {
          "type": "doubleAngle",
          "value": 136.37731221190455
        },
        "translateX": {
          "type": "doubleLinear",
          "value": -7.209667084786845
        },
        "rotateY": {
          "type": "doubleAngle",
          "value": -4.254821307343056
        },
        "scaleY": {
          "type": "double",
          "value": 1.0
        },
        "visibility": {
          "type": "bool",
          "value": true
        },
        "translateZ": {
          "type": "doubleLinear",
          "value": -47.57695364046355
        }
      }
    },
    "SK_Player_Weapon_Katana_001_rig:RootX_M": {
      "attrs": {
        "translateY": {
          "type": "doubleLinear",
          "value": 0.0
        },
        "rotateZ": {
          "type": "doubleAngle",
          "value": 0.0
        },
        "rotateX": {
          "type": "doubleAngle",
          "value": 0.0
        },
        "translateX": {
          "type": "doubleLinear",
          "value": 0.0
        },
        "rotateY": {
          "type": "doubleAngle",
          "value": 161.82992658343537
        },
        "visibility": {
          "type": "bool",
          "value": true
        },
        "translateZ": {
          "type": "doubleLinear",
          "value": 0.0
        }
      }
    },
    "SK_Player_Weapon_Katana_001_rig:Kakana1_ctrl": {
      "attrs": {
        "blendParent1": {
          "type": "double",
          "value": 1.0
        },
        "scaleZ": {
          "type": "double",
          "value": 1.0
        },
        "scaleX": {
          "type": "double",
          "value": 1.0
        },
        "translateY": {
          "type": "doubleLinear",
          "value": 134.46503917308064
        },
        "rotateZ": {
          "type": "doubleAngle",
          "value": -141.4909653825523
        },
        "rotateX": {
          "type": "doubleAngle",
          "value": 30.88263158617822
        },
        "translateX": {
          "type": "doubleLinear",
          "value": 148.3967893380774
        },
        "rotateY": {
          "type": "doubleAngle",
          "value": -27.53455776793622
        },
        "scaleY": {
          "type": "double",
          "value": 1.0
        },
        "visibility": {
          "type": "bool",
          "value": true
        },
        "translateZ": {
          "type": "doubleLinear",
          "value": -33.58805563687558
        }
      }
    },
    "SK_Player_Weapon_Katana_001_rig:Kakana1_ctrl2": {
      "attrs": {
        "scaleZ": {
          "type": "double",
          "value": 1.0
        },
        "scaleX": {
          "type": "double",
          "value": 1.0
        },
        "translateY": {
          "type": "doubleLinear",
          "value": 0.0
        },
        "rotateZ": {
          "type": "doubleAngle",
          "value": 0.0
        },
        "rotateX": {
          "type": "doubleAngle",
          "value": 0.0
        },
        "translateX": {
          "type": "doubleLinear",
          "value": 0.0
        },
        "rotateY": {
          "type": "doubleAngle",
          "value": 0.0
        },
        "scaleY": {
          "type": "double",
          "value": 1.0
        },
        "visibility": {
          "type": "bool",
          "value": true
        },
        "translateZ": {
          "type": "doubleLinear",
          "value": 0.0
        }
      }
    },
    "SK_Player_Weapon_Katana_001_rig:Scabbard1_ctrl": {
      "attrs": {
        "scaleZ": {
          "type": "double",
          "value": 1.0
        },
        "scaleX": {
          "type": "double",
          "value": 1.0
        },
        "translateY": {
          "type": "doubleLinear",
          "value": 0.0
        },
        "rotateZ": {
          "type": "doubleAngle",
          "value": 0.0
        },
        "rotateX": {
          "type": "doubleAngle",
          "value": 0.0
        },
        "translateX": {
          "type": "doubleLinear",
          "value": 0.0
        },
        "rotateY": {
          "type": "doubleAngle",
          "value": 0.0
        },
        "scaleY": {
          "type": "double",
          "value": 1.0
        },
        "visibility": {
          "type": "bool",
          "value": true
        },
        "translateZ": {
          "type": "doubleLinear",
          "value": 0.0
        }
      }
    },
    "SK_Player_Weapon_Katana_001_rig:Scabbard1_ctrl2": {
      "attrs": {
        "scaleZ": {
          "type": "double",
          "value": 1.0
        },
        "scaleX": {
          "type": "double",
          "value": 1.0
        },
        "translateY": {
          "type": "doubleLinear",
          "value": 0.0
        },
        "rotateZ": {
          "type": "doubleAngle",
          "value": 0.0
        },
        "rotateX": {
          "type": "doubleAngle",
          "value": 0.0
        },
        "translateX": {
          "type": "doubleLinear",
          "value": 0.0
        },
        "rotateY": {
          "type": "doubleAngle",
          "value": 0.0
        },
        "scaleY": {
          "type": "double",
          "value": 1.0
        },
        "visibility": {
          "type": "bool",
          "value": true
        },
        "translateZ": {
          "type": "doubleLinear",
          "value": 0.0
        }
      }
    }
  }
}